rtorrent_migrate/__init__.py
rtorrent_migrate/__main__.py
rtorrent_migrate/migrator.py
rtorrent_migrate/py.typed
rtorrent_migrate-1.0.0.dist-info/COPYING
rtorrent_migrate-1.0.0.dist-info/COPYING.LESSER
rtorrent_migrate-1.0.0.dist-info/METADATA
rtorrent_migrate-1.0.0.dist-info/WHEEL
rtorrent_migrate-1.0.0.dist-info/entry_points.txt
rtorrent_migrate-1.0.0.dist-info/top_level.txt
rtorrent_migrate-1.0.0.dist-info/RECORD
