Metadata-Version: 2.1
Name: rtorrent-migrate
Version: 1.0.0
Summary: rTorrent migration utility
Home-page: https://gitlab.com/adralioh/rtorrent-migrate
Author: Adralioh
License: UNKNOWN
Project-URL: Documentation, https://adralioh.gitlab.io/rtorrent-migrate
Keywords: bittorrent rtorrent
Platform: UNKNOWN
Classifier: Programming Language :: Python :: 3
Classifier: License :: OSI Approved :: GNU General Public License v3 (GPLv3)
Classifier: License :: OSI Approved :: GNU Lesser General Public License v3 (LGPLv3)
Classifier: Operating System :: OS Independent
Classifier: Environment :: Console
Classifier: Topic :: Communications :: File Sharing
Classifier: Topic :: Utilities
Classifier: Typing :: Typed
Requires-Python: >=3.6
Requires-Dist: benparse
